expert_ceylon/__init__.py
expert_ceylon/abstract.py
expert_ceylon/activation.py
expert_ceylon/agenda.py
expert_ceylon/conditionalelement.py
expert_ceylon/deffacts.py
expert_ceylon/engine.py
expert_ceylon/fact.py
expert_ceylon/factlist.py
expert_ceylon/fieldconstraint.py
expert_ceylon/frozenfact.py
expert_ceylon/operator.py
expert_ceylon/pattern.py
expert_ceylon/rule.py
expert_ceylon/shortcuts.py
expert_ceylon/strategies.py
expert_ceylon/utils.py
expert_ceylon/watchers.py
expert_ceylon/matchers/__init__.py
expert_ceylon/matchers/rete/__init__.py
expert_ceylon/matchers/rete/abstract.py
expert_ceylon/matchers/rete/check.py
expert_ceylon/matchers/rete/dnf.py
expert_ceylon/matchers/rete/mixins.py
expert_ceylon/matchers/rete/nodes.py
expert_ceylon/matchers/rete/token.py
expert_ceylon/matchers/rete/utils.py
expert_ceylon-2.0.0a2.dist-info/LICENSE
expert_ceylon-2.0.0a2.dist-info/METADATA
expert_ceylon-2.0.0a2.dist-info/WHEEL
expert_ceylon-2.0.0a2.dist-info/top_level.txt
expert_ceylon-2.0.0a2.dist-info/RECORD
