Metadata-Version: 2.1
Name: expert_ceylon
Version: 2.0.0a2
Summary: Expert Systems for Python Maintained by Ceylon AI
Home-page: https://github.com/ceylonai/experta-cylon
License: LGPLv3
Keywords: knowledge-based,inference,engine
Classifier: Programming Language :: Python :: 3.5
Classifier: Programming Language :: Python :: 3.6
Classifier: Programming Language :: Python :: 3.7
Classifier: Programming Language :: Python :: 3.8
Classifier: Programming Language :: Python :: Implementation :: PyPy
License-File: LICENSE
Requires-Dist: immutabledict ==1.0.0
Requires-Dist: schema ==0.6.7
